./.gitignore
./LICENSE
./PKG-INFO
./README.md
./config.py
./enrichment.py
./generator.py
./navigator.py
./parser.py
./pyproject.toml
./requirements.txt
./server.py
./utils.py
mcp_hivemind_server-1.2.0.dist-info/METADATA
mcp_hivemind_server-1.2.0.dist-info/WHEEL
mcp_hivemind_server-1.2.0.dist-info/entry_points.txt
mcp_hivemind_server-1.2.0.dist-info/licenses/LICENSE
mcp_hivemind_server-1.2.0.dist-info/RECORD
