Metadata-Version: 2.4
Name: mcp-hivemind-server
Version: 1.2.0
Summary: Intelligent MCP server that creates living documentation for codebases with AI-enriched context
Project-URL: Homepage, https://github.com/Jahanzaib-Kaleem/hive-mind-mcp
Project-URL: Repository, https://github.com/Jahanzaib-Kaleem/hive-mind-mcp
Project-URL: Issues, https://github.com/Jahanzaib-Kaleem/hive-mind-mcp/issues
Author-email: Jahanzaib Kaleem <jahanzaibkaleem@example.com>
License: MIT License
License-File: LICENSE
Keywords: ai,code-analysis,codebase,documentation,llm,mcp,model-context-protocol,tree-sitter
Classifier: Development Status :: 4 - Beta
Classifier: Intended Audience :: Developers
Classifier: License :: OSI Approved :: MIT License
Classifier: Programming Language :: Python :: 3
Classifier: Programming Language :: Python :: 3.11
Classifier: Programming Language :: Python :: 3.12
Classifier: Topic :: Software Development :: Code Generators
Classifier: Topic :: Software Development :: Documentation
Requires-Python: >=3.11
Requires-Dist: aiofiles>=23.0.0
Requires-Dist: mcp>=0.9.0
Requires-Dist: pyyaml>=6.0.0
Requires-Dist: tree-sitter-languages>=1.10.0
Requires-Dist: tree-sitter>=0.21.0
Provides-Extra: dev
Requires-Dist: pytest-asyncio>=0.21.0; extra == 'dev'
Requires-Dist: pytest>=7.0.0; extra == 'dev'
